algovanity/__init__.py
algovanity/__metadata__.py
algovanity/cli/__init__.py
algovanity/cli/logger.py
algovanity/cli/parser.py
algovanity/lib/__init__.py
algovanity/lib/helpers/__init__.py
algovanity/lib/helpers/matches.py
algovanity/lib/helpers/mproc.py
algovanity/lib/helpers/patterns.py
algovanity-0.1.dist-info/LICENSE
algovanity-0.1.dist-info/METADATA
algovanity-0.1.dist-info/WHEEL
algovanity-0.1.dist-info/entry_points.txt
algovanity-0.1.dist-info/top_level.txt
algovanity-0.1.dist-info/RECORD
