Metadata-Version: 2.1
Name: algovanity
Version: 0.1
Summary: generate vanity addresses for the Algorand blockchain
Home-page: https://github.com/nxet/algovanity
Author: nxet
Author-email: nxet821@protonmail.com
License: UNKNOWN
Project-URL: Bug Tracker, https://github.com/nxet/algovanity/issues
Platform: UNKNOWN
Classifier: Programming Language :: Python :: 3
Classifier: Operating System :: POSIX :: Linux
Classifier: Environment :: Console
Classifier: Natural Language :: English
Requires-Python: >=3.7.3
License-File: LICENSE
Requires-Dist: py-algorand-sdk (>=1.7.0)
